mcp_simple_openai_assistant/__init__.py
mcp_simple_openai_assistant/__main__.py
mcp_simple_openai_assistant/app.py
mcp_simple_openai_assistant/assistant_manager.py
mcp_simple_openai_assistant/thread_store.py
mcp_simple_openai_assistant-0.4.1.dist-info/licenses/LICENSE
mcp_simple_openai_assistant-0.4.1.dist-info/METADATA
mcp_simple_openai_assistant-0.4.1.dist-info/WHEEL
mcp_simple_openai_assistant-0.4.1.dist-info/entry_points.txt
mcp_simple_openai_assistant-0.4.1.dist-info/top_level.txt
mcp_simple_openai_assistant-0.4.1.dist-info/RECORD
